polystore/__init__.py
polystore/async_init.py
polystore/atomic.py
polystore/backend_registry.py
polystore/base.py
polystore/config.py
polystore/constants.py
polystore/disk.py
polystore/exceptions.py
polystore/fiji_stream.py
polystore/filemanager.py
polystore/formats.py
polystore/lazy_imports.py
polystore/memory.py
polystore/metadata_migration.py
polystore/metadata_writer.py
polystore/napari_stream.py
polystore/omero_local.py
polystore/registry.py
polystore/roi.py
polystore/roi_converters.py
polystore/streaming.py
polystore/streaming_constants.py
polystore/utils.py
polystore/virtual_workspace.py
polystore/zarr.py
polystore/zmq_config.py
polystore-0.1.7.dist-info/licenses/LICENSE
polystore-0.1.7.dist-info/METADATA
polystore-0.1.7.dist-info/WHEEL
polystore-0.1.7.dist-info/top_level.txt
polystore-0.1.7.dist-info/RECORD
